{
  "offers": [
    {
      "id": "offer-1",
      "name": "Fresh Vegetable Bundle",
      "description": "Mixed seasonal vegetables including carrots, broccoli, spinach, and more!",
      "image": "./images/organic-img/asparagus.jpg",
      "category": "weekly",
      "badge": "-25% OFF",
      "badgeType": "discount",
      "currentPrice": 18.99,
      "originalPrice": 24.99,
      "savings": 6.00,
      "validUntil": "March 31, 2024",
      "inStock": true,
      "quantity": "1 bundle",
      "featured": false
    },
    {
      "id": "offer-2", 
      "name": "Organic Broccoli Pack",
      "description": "Fresh organic broccoli heads, perfect for healthy meals and salads!",
      "image": "./images/organic-img/organic-broccoli.jpg",
      "category": "weekly",
      "badge": "-30% OFF",
      "badgeType": "discount",
      "currentPrice": 12.99,
      "originalPrice": 18.50,
      "savings": 5.51,
      "validUntil": "April 2, 2024",
      "inStock": true,
      "quantity": "2 lbs",
      "featured": false
    },
    {
      "id": "offer-3",
      "name": "Organic Apples",
      "description": "Buy 1 bag of organic apples, get another bag absolutely free!",
      "image": "./images/organic-img/cherries.jpg",
      "category": "bogo",
      "badge": "BOGO",
      "badgeType": "bogo",
      "currentPrice": 4.99,
      "originalPrice": 9.98,
      "savings": 4.99,
      "validUntil": "April 5, 2024",
      "inStock": true,
      "quantity": "2 bags",
      "featured": false
    },
    {
      "id": "offer-4",
      "name": "Fresh Strawberries",
      "description": "Buy 1 pack of fresh strawberries, get another pack completely free!",
      "image": "./images/organic-img/ripe-strawberries.jpg",
      "category": "bogo",
      "badge": "BOGO",
      "badgeType": "bogo",
      "currentPrice": 6.99,
      "originalPrice": 13.98,
      "savings": 6.99,
      "validUntil": "April 7, 2024",
      "inStock": true,
      "quantity": "2 packs",
      "featured": false
    },
    {
      "id": "offer-5",
      "name": "Organic Juice Pack",
      "description": "6 bottles of assorted organic juices - orange, apple, carrot, and green juice.",
      "image": "./images/organic-img/mixed-berry-juice.jpg",
      "category": "bundles",
      "badge": "LIMITED",
      "badgeType": "limited",
      "currentPrice": 29.99,
      "originalPrice": 41.94,
      "savings": 11.95,
      "validUntil": "March 28, 2024",
      "inStock": true,
      "quantity": "6 bottles",
      "featured": false
    },
    {
      "id": "offer-6",
      "name": "Dairy Essentials Bundle",
      "description": "Complete dairy bundle including yogurt, milk, cheese, and butter from organic farms.",
      "image": "./images/organic-img/greek-yogurt.jpg",
      "category": "bundles",
      "badge": "LIMITED",
      "badgeType": "limited",
      "currentPrice": 24.99,
      "originalPrice": 35.50,
      "savings": 10.51,
      "validUntil": "March 30, 2024",
      "inStock": true,
      "quantity": "1 bundle",
      "featured": false
    },
    {
      "id": "offer-7",
      "name": "Organic Dried Fruits",
      "description": "Mix of organic dried fruits - perfect for snacking or baking!",
      "image": "./images/organic-img/dried-mango-slices.jpg",
      "category": "clearance",
      "badge": "-40% OFF",
      "badgeType": "discount",
      "currentPrice": 12.99,
      "originalPrice": 21.99,
      "savings": 9.00,
      "validUntil": "March 25, 2024",
      "inStock": true,
      "quantity": "1 lb",
      "featured": false
    },
    {
      "id": "offer-8",
      "name": "Organic Oatmeal Cookies",
      "description": "Delicious organic oatmeal cookies with natural sweeteners and whole grains.",
      "image": "./images/organic-img/oatmeal-cookies.jpg",
      "category": "clearance",
      "badge": "-35% OFF",
      "badgeType": "discount",
      "currentPrice": 8.99,
      "originalPrice": 13.85,
      "savings": 4.86,
      "validUntil": "March 26, 2024",
      "inStock": true,
      "quantity": "12 cookies",
      "featured": false
    },
    {
      "id": "offer-9",
      "name": "Seasonal Fruit Collection",
      "description": "Fresh seasonal fruits handpicked from local farms - strawberries, peaches, and more!",
      "image": "./images/organic-img/seasonal-fruits.jpg",
      "category": "seasonal",
      "badge": "SEASONAL",
      "badgeType": "seasonal",
      "currentPrice": 34.99,
      "originalPrice": 49.99,
      "savings": 15.00,
      "validUntil": "Limited seasonal availability",
      "inStock": true,
      "quantity": "5 lbs",
      "featured": false
    },
    {
      "id": "offer-10",
      "name": "Spring Vegetable Mix",
      "description": "Fresh spring vegetables including kale, spinach, and early season greens.",
      "image": "./images/organic-img/green-kale.jpg",
      "category": "seasonal",
      "badge": "SEASONAL",
      "badgeType": "seasonal",
      "currentPrice": 22.99,
      "originalPrice": 32.50,
      "savings": 9.51,
      "validUntil": "Limited spring availability",
      "inStock": true,
      "quantity": "3 lbs",
      "featured": false
    },
    {
      "id": "offer-11",
      "name": "$50 Gift Voucher",
      "description": "Perfect gift for health-conscious friends and family. Redeemable on all organic products!",
      "image": "./images/organic-img/gift-basket.jpg",
      "category": "gift",
      "badge": "GIFT",
      "badgeType": "gift",
      "currentPrice": 45.00,
      "originalPrice": 50.00,
      "savings": 5.00,
      "validUntil": "Valid for 1 year",
      "inStock": true,
      "quantity": "1 voucher",
      "featured": false
    },
    {
      "id": "offer-12",
      "name": "$100 Gift Voucher",
      "description": "Premium gift voucher for larger orders. Perfect for families and bulk purchases!",
      "image": "./images/organic-img/coconut-chips.jpg",
      "category": "gift",
      "badge": "GIFT",
      "badgeType": "gift",
      "currentPrice": 85.00,
      "originalPrice": 100.00,
      "savings": 15.00,
      "validUntil": "Valid for 1 year",
      "inStock": true,
      "quantity": "1 voucher",
      "featured": false
    },
    {
      "id": "offer-13",
      "name": "Premium Organic Fruit Box",
      "description": "20 lbs of fresh seasonal fruits delivered to your door!",
      "image": "./images/organic-img/green-grapes.jpg",
      "category": "featured",
      "badge": "DEAL OF THE WEEK",
      "badgeType": "featured",
      "currentPrice": 59.99,
      "originalPrice": 89.99,
      "savings": 30.00,
      "validUntil": "Limited time offer",
      "inStock": true,
      "quantity": "20 lbs",
      "featured": true
    },
    {
      "id": "offer-14",
      "name": "Family Pack",
      "description": "5 lbs Fruits + 5 lbs Vegetables + 4 Juices - Perfect for families!",
      "image": "./images/organic-img/ripe-strawberries.jpg",
      "category": "bundles",
      "badge": "BUNDLE",
      "badgeType": "bundle",
      "currentPrice": 45.99,
      "originalPrice": 60.99,
      "savings": 15.00,
      "validUntil": "Ongoing",
      "inStock": true,
      "quantity": "1 pack",
      "featured": false
    },
    {
      "id": "offer-15",
      "name": "Health Boost Bundle",
      "description": "Superfoods + Supplements + Herbal Teas - Boost your health!",
      "image": "./images/organic-img/green-kale.jpg",
      "category": "bundles",
      "badge": "BUNDLE",
      "badgeType": "bundle",
      "currentPrice": 39.99,
      "originalPrice": 59.99,
      "savings": 20.00,
      "validUntil": "Ongoing",
      "inStock": true,
      "quantity": "1 bundle",
      "featured": false
    },
    {
      "id": "offer-16",
      "name": "Snack Lover Bundle",
      "description": "Oatmeal Cookies + Coconut Chips + Rice Crackers - Perfect for snacking!",
      "image": "./images/organic-img/oatmeal-cookies.jpg",
      "category": "bundles",
      "badge": "BUNDLE",
      "badgeType": "bundle",
      "currentPrice": 19.99,
      "originalPrice": 29.99,
      "savings": 10.00,
      "validUntil": "Ongoing",
      "inStock": true,
      "quantity": "1 bundle",
      "featured": false
    }
  ]
}
